{"Modules":[{"Key":"VPC_module.vpc","Source":"registry.terraform.io/terraform-aws-modules/vpc/aws","Version":"3.14.0","Dir":".terraform/modules/VPC_module.vpc"},{"Key":"ec2_module","Source":"./modules/ec2-module","Dir":"modules/ec2-module"},{"Key":"ec2_module.ec2_instance","Source":"registry.terraform.io/terraform-aws-modules/ec2-instance/aws","Version":"3.5.0","Dir":".terraform/modules/ec2_module.ec2_instance"},{"Key":"iam_module","Source":"./modules/iam-module","Dir":"modules/iam-module"},{"Key":"security_groups_module","Source":"./modules/security-group-module","Dir":"modules/security-group-module"},{"Key":"shared_vars","Source":"./modules/shared-vars","Dir":"modules/shared-vars"},{"Key":"","Source":"","Dir":"."},{"Key":"VPC_module","Source":"./modules/vpc-module","Dir":"modules/vpc-module"}]}